googoal/__init__.py
googoal/config.py
googoal/defaults.yml
googoal/googoal.py
googoal/odsmail.py
googoal-0.0.1.dist-info/METADATA
googoal-0.0.1.dist-info/WHEEL
googoal-0.0.1.dist-info/entry_points.txt
googoal-0.0.1.dist-info/top_level.txt
googoal-0.0.1.dist-info/RECORD
