Metadata-Version: 2.1
Name: googoal
Version: 0.0.1
Summary: Python software for interfacing with google services.
Home-page: https://github.com/lawrennd/googoal
Author: Neil D. Lawrence
Author-email: lawrennd@gmail.com
License: MIT
Platform: UNKNOWN
Classifier: License :: OSI Approved :: MIT License
Classifier: Programming Language :: Python
Classifier: Programming Language :: Python :: 3
Classifier: Programming Language :: Python :: 3.6
Classifier: Programming Language :: Python :: Implementation :: CPython
Classifier: Programming Language :: Python :: Implementation :: PyPy
Requires-Python: >=3.6.0
Requires-Dist: PyYAML
Requires-Dist: pandas
Requires-Dist: oauth2client
Requires-Dist: gspread
Requires-Dist: gdata
Requires-Dist: google-api-python-client
Requires-Dist: notutils
